<featureType>
  <id>FeatureTypeInfoImpl--5706e53b:1814c6b2c20:-50c0</id>
  <name>q_peta_lahan_petani</name>
  <nativeName>q_peta_lahan_petani</nativeName>
  <namespace>
    <id>NamespaceInfoImpl--5706e53b:1814c6b2c20:-50c2</id>
  </namespace>
  <title>q_peta_lahan_petani</title>
  <keywords>
    <string>features</string>
    <string>q_peta_lahan_petani</string>
  </keywords>
  <srs>EPSG:4326</srs>
  <nativeBoundingBox>
    <minx>-1.0</minx>
    <maxx>0.0</maxx>
    <miny>-1.0</miny>
    <maxy>0.0</maxy>
  </nativeBoundingBox>
  <latLonBoundingBox>
    <minx>-1.0</minx>
    <maxx>0.0</maxx>
    <miny>-1.0</miny>
    <maxy>0.0</maxy>
    <crs>EPSG:4326</crs>
  </latLonBoundingBox>
  <projectionPolicy>FORCE_DECLARED</projectionPolicy>
  <enabled>true</enabled>
  <store class="dataStore">
    <id>DataStoreInfoImpl--5706e53b:1814c6b2c20:-50c1</id>
  </store>
  <serviceConfiguration>false</serviceConfiguration>
  <simpleConversionEnabled>false</simpleConversionEnabled>
  <maxFeatures>0</maxFeatures>
  <numDecimals>0</numDecimals>
  <padWithZeros>false</padWithZeros>
  <forcedDecimal>false</forcedDecimal>
  <overridingServiceSRS>false</overridingServiceSRS>
  <skipNumberMatched>false</skipNumberMatched>
  <circularArcPresent>false</circularArcPresent>
</featureType>